<?xml version="1.0" encoding="UTF-8"?><users><user><id>1</id><username>DEV                                                                                                 </username><password>DEV2016                                                                                             </password><age>27</age></user><user><id>3</id><username>JAYESH                                                                                              </username><password>JAY2016                                                                                             </password><age>35</age></user><user><id>4</id><username>KETAN                                                                                               </username><password>KET2016                                                                                             </password><age>40</age></user><user><id>5</id><username>KOMAL                                                                                               </username><password>KOM2016                                                                                             </password><age>22</age></user></users>